coin_remitter/__init__.py
coin_remitter/main.py
coin_remitter-0.1.1.dist-info/METADATA
coin_remitter-0.1.1.dist-info/WHEEL
coin_remitter-0.1.1.dist-info/top_level.txt
coin_remitter-0.1.1.dist-info/RECORD
