Metadata-Version: 2.1
Name: coin_remitter
Version: 0.1.1
Summary: A Python SDK for integrating with the CoinRemitter cryptocurrency payment gateway API.
Home-page: https://github.com/glizzykingdreko/coinremitter-sdk
Author: glizzykingdreko
Author-email: glizzykingdreko@example.com
Project-URL: Documentation, https://coinremitter.com/docs
Project-URL: Source, https://github.com/glizzykingdreko/coinremitter-sdk
Project-URL: Tracker, https://github.com/glizzykingdreko/coinremitter-sdk/issues
Keywords: cryptocurrency payment gateway coin remitter api sdk crypto
Classifier: Development Status :: 4 - Beta
Classifier: Intended Audience :: Developers
Classifier: Topic :: Software Development :: Libraries :: Python Modules
Classifier: License :: OSI Approved :: MIT License
Classifier: Programming Language :: Python :: 3
Classifier: Programming Language :: Python :: 3.7
Classifier: Programming Language :: Python :: 3.8
Classifier: Programming Language :: Python :: 3.9
Classifier: Programming Language :: Python :: 3.10
Requires-Python: >=3.7
Requires-Dist: requests >=2.25.1
